{
  "instances": [
    {
      "instance_id": 1,
      "class_name": "traffic_cone",
      "class_id": 8,
      "score": 0.6160128712654114,
      "bbox": [
        1190.65087890625,
        528.8265991210938,
        1207.1265869140625,
        552.478271484375
      ],
      "mask_area": 297
    },
    {
      "instance_id": 2,
      "class_name": "traffic_cone",
      "class_id": 8,
      "score": 0.7191539406776428,
      "bbox": [
        864.6787719726562,
        508.55841064453125,
        878.383056640625,
        539.1087646484375
      ],
      "mask_area": 314
    },
    {
      "instance_id": 3,
      "class_name": "traffic_cone",
      "class_id": 8,
      "score": 0.7381991147994995,
      "bbox": [
        1222.1668701171875,
        520.1195678710938,
        1238.5550537109375,
        555.4977416992188
      ],
      "mask_area": 392
    },
    {
      "instance_id": 4,
      "class_name": "car",
      "class_id": 0,
      "score": 0.7531012296676636,
      "bbox": [
        790.1957397460938,
        470.4773254394531,
        810.0848388671875,
        486.2493591308594
      ],
      "mask_area": 277
    },
    {
      "instance_id": 5,
      "class_name": "traffic_cone",
      "class_id": 8,
      "score": 0.7585071325302124,
      "bbox": [
        1152.49267578125,
        516.3989868164062,
        1166.4163818359375,
        547.2350463867188
      ],
      "mask_area": 284
    },
    {
      "instance_id": 6,
      "class_name": "traffic_cone",
      "class_id": 8,
      "score": 0.770653486251831,
      "bbox": [
        880.9115600585938,
        515.8504028320312,
        896.2147827148438,
        552.2716674804688
      ],
      "mask_area": 377
    },
    {
      "instance_id": 7,
      "class_name": "traffic_cone",
      "class_id": 8,
      "score": 0.7822840809822083,
      "bbox": [
        1244.9378662109375,
        522.0447998046875,
        1261.99072265625,
        558.0226440429688
      ],
      "mask_area": 395
    },
    {
      "instance_id": 8,
      "class_name": "traffic_cone",
      "class_id": 8,
      "score": 0.7990567088127136,
      "bbox": [
        1283.5103759765625,
        524.8324584960938,
        1302.27197265625,
        564.8709716796875
      ],
      "mask_area": 445
    },
    {
      "instance_id": 9,
      "class_name": "traffic_cone",
      "class_id": 8,
      "score": 0.8028157353401184,
      "bbox": [
        1310.2017822265625,
        527.842529296875,
        1331.2449951171875,
        569.0363159179688
      ],
      "mask_area": 531
    },
    {
      "instance_id": 10,
      "class_name": "traffic_cone",
      "class_id": 8,
      "score": 0.8126432299613953,
      "bbox": [
        1343.990478515625,
        531.3975219726562,
        1365.188720703125,
        575.2374877929688
      ],
      "mask_area": 565
    },
    {
      "instance_id": 11,
      "class_name": "traffic_cone",
      "class_id": 8,
      "score": 0.8214174509048462,
      "bbox": [
        908.3592529296875,
        529.6315307617188,
        931.4112548828125,
        577.4642333984375
      ],
      "mask_area": 661
    },
    {
      "instance_id": 12,
      "class_name": "traffic_cone",
      "class_id": 8,
      "score": 0.8221092224121094,
      "bbox": [
        1434.0384521484375,
        547.3762817382812,
        1461.144775390625,
        590.0725708007812
      ],
      "mask_area": 681
    },
    {
      "instance_id": 13,
      "class_name": "traffic_cone",
      "class_id": 8,
      "score": 0.8295726180076599,
      "bbox": [
        1382.8427734375,
        536.21435546875,
        1406.6209716796875,
        581.8930053710938
      ],
      "mask_area": 607
    },
    {
      "instance_id": 14,
      "class_name": "traffic_cone",
      "class_id": 8,
      "score": 0.842603325843811,
      "bbox": [
        1502.21826171875,
        807.4039916992188,
        1558.821533203125,
        900.3095092773438
      ],
      "mask_area": 3700
    },
    {
      "instance_id": 15,
      "class_name": "traffic_cone",
      "class_id": 8,
      "score": 0.8482550978660583,
      "bbox": [
        1504.416748046875,
        545.5643310546875,
        1533.3056640625,
        602.4031982421875
      ],
      "mask_area": 913
    },
    {
      "instance_id": 16,
      "class_name": "traffic_cone",
      "class_id": 8,
      "score": 0.8632116317749023,
      "bbox": [
        939.5367431640625,
        546.80224609375,
        972.3902587890625,
        612.6054077148438
      ],
      "mask_area": 1131
    },
    {
      "instance_id": 17,
      "class_name": "traffic_cone",
      "class_id": 8,
      "score": 0.9053124189376831,
      "bbox": [
        1033.50830078125,
        603.7089233398438,
        1094.771728515625,
        717.54345703125
      ],
      "mask_area": 3492
    },
    {
      "instance_id": 18,
      "class_name": "car",
      "class_id": 0,
      "score": 0.9446921944618225,
      "bbox": [
        184.01638793945312,
        378.0148620605469,
        694.0018920898438,
        716.656005859375
      ],
      "mask_area": 137654
    }
  ]
}