{
  "instances": [
    {
      "instance_id": 1,
      "class_name": "pedestrian",
      "class_id": 5,
      "score": 0.6346237063407898,
      "bbox": [
        782.779296875,
        464.6163330078125,
        827.1753540039062,
        582.1679077148438
      ],
      "mask_area": 3428
    },
    {
      "instance_id": 2,
      "class_name": "pedestrian",
      "class_id": 5,
      "score": 0.7020424008369446,
      "bbox": [
        1016.778076171875,
        480.69964599609375,
        1058.893310546875,
        603.6232299804688
      ],
      "mask_area": 3368
    },
    {
      "instance_id": 3,
      "class_name": "pedestrian",
      "class_id": 5,
      "score": 0.7366542816162109,
      "bbox": [
        934.0184326171875,
        463.7536315917969,
        960.0850219726562,
        547.9066162109375
      ],
      "mask_area": 1501
    },
    {
      "instance_id": 4,
      "class_name": "car",
      "class_id": 0,
      "score": 0.7699883580207825,
      "bbox": [
        699.5065307617188,
        472.0948181152344,
        773.7510375976562,
        534.1969604492188
      ],
      "mask_area": 2799
    },
    {
      "instance_id": 5,
      "class_name": "bus",
      "class_id": 2,
      "score": 0.8101385831832886,
      "bbox": [
        539.3428955078125,
        356.5208435058594,
        652.89599609375,
        529.6392822265625
      ],
      "mask_area": 14934
    },
    {
      "instance_id": 6,
      "class_name": "pedestrian",
      "class_id": 5,
      "score": 0.8266522288322449,
      "bbox": [
        1269.895263671875,
        441.64208984375,
        1333.57666015625,
        674.868896484375
      ],
      "mask_area": 8448
    },
    {
      "instance_id": 7,
      "class_name": "pedestrian",
      "class_id": 5,
      "score": 0.8337818384170532,
      "bbox": [
        1148.6439208984375,
        476.2928771972656,
        1222.388671875,
        690.7703857421875
      ],
      "mask_area": 9344
    },
    {
      "instance_id": 8,
      "class_name": "car",
      "class_id": 0,
      "score": 0.8595193028450012,
      "bbox": [
        621.5989379882812,
        479.57366943359375,
        735.833740234375,
        559.0218505859375
      ],
      "mask_area": 6631
    },
    {
      "instance_id": 9,
      "class_name": "car",
      "class_id": 0,
      "score": 0.8969072699546814,
      "bbox": [
        465.7366638183594,
        476.9433898925781,
        593.46923828125,
        560.3597412109375
      ],
      "mask_area": 8332
    }
  ]
}