{
  "instances": [
    {
      "instance_id": 1,
      "class_name": "car",
      "class_id": 0,
      "score": 0.5249511003494263,
      "bbox": [
        912.2197265625,
        481.04656982421875,
        945.6011962890625,
        537.040283203125
      ],
      "mask_area": 52
    },
    {
      "instance_id": 2,
      "class_name": "car",
      "class_id": 0,
      "score": 0.6083284020423889,
      "bbox": [
        911.1139526367188,
        483.56634521484375,
        1061.1854248046875,
        541.1851196289062
      ],
      "mask_area": 730
    },
    {
      "instance_id": 3,
      "class_name": "car",
      "class_id": 0,
      "score": 0.6267331838607788,
      "bbox": [
        1004.4553833007812,
        503.586669921875,
        1062.6014404296875,
        540.802978515625
      ],
      "mask_area": 1752
    },
    {
      "instance_id": 4,
      "class_name": "car",
      "class_id": 0,
      "score": 0.6539842486381531,
      "bbox": [
        859.1119995117188,
        471.989013671875,
        935.8564453125,
        504.9739685058594
      ],
      "mask_area": 878
    },
    {
      "instance_id": 5,
      "class_name": "car",
      "class_id": 0,
      "score": 0.6544084548950195,
      "bbox": [
        672.7435302734375,
        469.6474609375,
        720.6026611328125,
        499.9167175292969
      ],
      "mask_area": 950
    },
    {
      "instance_id": 6,
      "class_name": "car",
      "class_id": 0,
      "score": 0.6702092289924622,
      "bbox": [
        713.6947021484375,
        478.98388671875,
        768.10546875,
        504.3651123046875
      ],
      "mask_area": 1101
    },
    {
      "instance_id": 7,
      "class_name": "car",
      "class_id": 0,
      "score": 0.6818622350692749,
      "bbox": [
        794.6912231445312,
        471.17205810546875,
        831.2774658203125,
        505.24395751953125
      ],
      "mask_area": 1041
    },
    {
      "instance_id": 8,
      "class_name": "car",
      "class_id": 0,
      "score": 0.7247790098190308,
      "bbox": [
        652.7142944335938,
        475.49273681640625,
        701.53173828125,
        508.0036926269531
      ],
      "mask_area": 936
    },
    {
      "instance_id": 9,
      "class_name": "car",
      "class_id": 0,
      "score": 0.7626441717147827,
      "bbox": [
        -0.7307648658752441,
        473.555908203125,
        32.40757751464844,
        509.6423645019531
      ],
      "mask_area": 1021
    },
    {
      "instance_id": 10,
      "class_name": "pedestrian",
      "class_id": 5,
      "score": 0.8402295708656311,
      "bbox": [
        928.714111328125,
        463.1395568847656,
        954.3858642578125,
        588.2693481445312
      ],
      "mask_area": 2035
    },
    {
      "instance_id": 11,
      "class_name": "car",
      "class_id": 0,
      "score": 0.8813812136650085,
      "bbox": [
        1558.148193359375,
        496.8277282714844,
        1602.5418701171875,
        559.4072265625
      ],
      "mask_area": 2125
    },
    {
      "instance_id": 12,
      "class_name": "pedestrian",
      "class_id": 5,
      "score": 0.9069622755050659,
      "bbox": [
        766.5090942382812,
        477.10791015625,
        802.7801513671875,
        615.3975830078125
      ],
      "mask_area": 3247
    },
    {
      "instance_id": 13,
      "class_name": "pedestrian",
      "class_id": 5,
      "score": 0.9277095794677734,
      "bbox": [
        1154.472412109375,
        453.4384460449219,
        1227.579345703125,
        676.9606323242188
      ],
      "mask_area": 7296
    },
    {
      "instance_id": 14,
      "class_name": "bus",
      "class_id": 2,
      "score": 0.9293733835220337,
      "bbox": [
        1270.640625,
        402.13214111328125,
        1602.356689453125,
        546.306884765625
      ],
      "mask_area": 32838
    },
    {
      "instance_id": 15,
      "class_name": "pedestrian",
      "class_id": 5,
      "score": 0.9348229765892029,
      "bbox": [
        844.5745239257812,
        464.4755554199219,
        915.89697265625,
        638.117919921875
      ],
      "mask_area": 5807
    },
    {
      "instance_id": 16,
      "class_name": "pedestrian",
      "class_id": 5,
      "score": 0.9387245178222656,
      "bbox": [
        1332.1453857421875,
        466.8225402832031,
        1410.5870361328125,
        679.5957641601562
      ],
      "mask_area": 9217
    },
    {
      "instance_id": 17,
      "class_name": "pedestrian",
      "class_id": 5,
      "score": 0.9459995627403259,
      "bbox": [
        1056.4554443359375,
        440.6048278808594,
        1119.3037109375,
        637.3782348632812
      ],
      "mask_area": 7438
    },
    {
      "instance_id": 18,
      "class_name": "pedestrian",
      "class_id": 5,
      "score": 0.949695885181427,
      "bbox": [
        1183.2911376953125,
        429.2594299316406,
        1306.19873046875,
        708.0670166015625
      ],
      "mask_area": 14739
    },
    {
      "instance_id": 19,
      "class_name": "car",
      "class_id": 0,
      "score": 0.9584878087043762,
      "bbox": [
        -2.1753311157226562,
        526.4931640625,
        996.18798828125,
        897.048583984375
      ],
      "mask_area": 235834
    }
  ]
}