{
  "instances": [
    {
      "instance_id": 1,
      "class_name": "pedestrian",
      "class_id": 5,
      "score": 0.735475480556488,
      "bbox": [
        1064.9527587890625,
        439.88287353515625,
        1103.8663330078125,
        472.5531311035156
      ],
      "mask_area": 776
    },
    {
      "instance_id": 2,
      "class_name": "car",
      "class_id": 0,
      "score": 0.7390459775924683,
      "bbox": [
        840.263916015625,
        440.6801452636719,
        994.8095092773438,
        482.6327819824219
      ],
      "mask_area": 4043
    },
    {
      "instance_id": 3,
      "class_name": "pedestrian",
      "class_id": 5,
      "score": 0.762215256690979,
      "bbox": [
        316.16168212890625,
        415.6562194824219,
        356.7548828125,
        453.741455078125
      ],
      "mask_area": 861
    },
    {
      "instance_id": 4,
      "class_name": "car",
      "class_id": 0,
      "score": 0.7930917739868164,
      "bbox": [
        1129.4134521484375,
        440.311279296875,
        1202.9698486328125,
        471.12127685546875
      ],
      "mask_area": 1593
    },
    {
      "instance_id": 5,
      "class_name": "pedestrian",
      "class_id": 5,
      "score": 0.7999100685119629,
      "bbox": [
        1027.879150390625,
        434.8115234375,
        1056.0794677734375,
        520.2006225585938
      ],
      "mask_area": 1450
    },
    {
      "instance_id": 6,
      "class_name": "traffic_cone",
      "class_id": 8,
      "score": 0.8011195063591003,
      "bbox": [
        246.52769470214844,
        471.20086669921875,
        265.0056457519531,
        512.3660278320312
      ],
      "mask_area": 480
    },
    {
      "instance_id": 7,
      "class_name": "car",
      "class_id": 0,
      "score": 0.9478009939193726,
      "bbox": [
        284.325927734375,
        416.3765563964844,
        549.6715087890625,
        526.1973876953125
      ],
      "mask_area": 20618
    }
  ]
}