{
  "instances": [
    {
      "instance_id": 1,
      "class_name": "barrier",
      "class_id": 9,
      "score": 0.5536843538284302,
      "bbox": [
        469.7127380371094,
        548.5963745117188,
        550.2734985351562,
        677.5520629882812
      ],
      "mask_area": 1451
    },
    {
      "instance_id": 2,
      "class_name": "barrier",
      "class_id": 9,
      "score": 0.5673545002937317,
      "bbox": [
        76.774658203125,
        499.93365478515625,
        228.90109252929688,
        534.5953979492188
      ],
      "mask_area": 4046
    },
    {
      "instance_id": 3,
      "class_name": "barrier",
      "class_id": 9,
      "score": 0.6942799091339111,
      "bbox": [
        568.3535766601562,
        530.9530639648438,
        751.57470703125,
        549.4093017578125
      ],
      "mask_area": 2708
    },
    {
      "instance_id": 4,
      "class_name": "barrier",
      "class_id": 9,
      "score": 0.7035952210426331,
      "bbox": [
        541.7106323242188,
        545.2868041992188,
        720.4957275390625,
        683.8572387695312
      ],
      "mask_area": 5519
    },
    {
      "instance_id": 5,
      "class_name": "pedestrian",
      "class_id": 5,
      "score": 0.725750207901001,
      "bbox": [
        849.0531005859375,
        478.11529541015625,
        876.79150390625,
        545.6114501953125
      ],
      "mask_area": 946
    },
    {
      "instance_id": 6,
      "class_name": "barrier",
      "class_id": 9,
      "score": 0.8110308647155762,
      "bbox": [
        250.45175170898438,
        549.2979125976562,
        543.9136352539062,
        690.3099975585938
      ],
      "mask_area": 28877
    },
    {
      "instance_id": 7,
      "class_name": "barrier",
      "class_id": 9,
      "score": 0.8762141466140747,
      "bbox": [
        1546.5343017578125,
        531.9325561523438,
        1601.9677734375,
        655.760498046875
      ],
      "mask_area": 5387
    },
    {
      "instance_id": 8,
      "class_name": "traffic_cone",
      "class_id": 8,
      "score": 0.87701416015625,
      "bbox": [
        214.42031860351562,
        588.6583862304688,
        250.23036193847656,
        674.7379760742188
      ],
      "mask_area": 1969
    },
    {
      "instance_id": 9,
      "class_name": "pedestrian",
      "class_id": 5,
      "score": 0.8855766654014587,
      "bbox": [
        0.6170764565467834,
        488.96728515625,
        41.09073257446289,
        600.2139282226562
      ],
      "mask_area": 2649
    },
    {
      "instance_id": 10,
      "class_name": "barrier",
      "class_id": 9,
      "score": 0.8922213912010193,
      "bbox": [
        580.6341552734375,
        549.4061279296875,
        860.0526733398438,
        705.1785278320312
      ],
      "mask_area": 34057
    },
    {
      "instance_id": 11,
      "class_name": "barrier",
      "class_id": 9,
      "score": 0.9115722179412842,
      "bbox": [
        854.1785888671875,
        545.3331909179688,
        1119.7607421875,
        691.717529296875
      ],
      "mask_area": 33290
    },
    {
      "instance_id": 12,
      "class_name": "barrier",
      "class_id": 9,
      "score": 0.9119027256965637,
      "bbox": [
        1111.7930908203125,
        540.3787841796875,
        1352.8697509765625,
        679.9099731445312
      ],
      "mask_area": 27226
    },
    {
      "instance_id": 13,
      "class_name": "barrier",
      "class_id": 9,
      "score": 0.9123595356941223,
      "bbox": [
        1339.9833984375,
        534.3670043945312,
        1561.57763671875,
        666.8224487304688
      ],
      "mask_area": 25986
    },
    {
      "instance_id": 14,
      "class_name": "traffic_cone",
      "class_id": 8,
      "score": 0.9251273274421692,
      "bbox": [
        293.5303649902344,
        595.2098999023438,
        365.4961242675781,
        710.1694946289062
      ],
      "mask_area": 3473
    },
    {
      "instance_id": 15,
      "class_name": "traffic_cone",
      "class_id": 8,
      "score": 0.9289121031761169,
      "bbox": [
        439.8651123046875,
        594.0241088867188,
        502.911865234375,
        707.4996948242188
      ],
      "mask_area": 3361
    }
  ]
}