{
  "instances": [
    {
      "instance_id": 1,
      "class_name": "pedestrian",
      "class_id": 5,
      "score": 0.8479823470115662,
      "bbox": [
        834.251708984375,
        410.04248046875,
        907.7809448242188,
        650.5724487304688
      ],
      "mask_area": 7115
    },
    {
      "instance_id": 2,
      "class_name": "pedestrian",
      "class_id": 5,
      "score": 0.9350513815879822,
      "bbox": [
        887.65869140625,
        405.25189208984375,
        1000.9378662109375,
        669.7839965820312
      ],
      "mask_area": 11938
    }
  ]
}