{
  "instances": [
    {
      "instance_id": 1,
      "class_name": "car",
      "class_id": 0,
      "score": 0.5787304639816284,
      "bbox": [
        1119.97509765625,
        481.5376892089844,
        1156.48779296875,
        535.597900390625
      ],
      "mask_area": 1528
    },
    {
      "instance_id": 2,
      "class_name": "pedestrian",
      "class_id": 5,
      "score": 0.6745831966400146,
      "bbox": [
        1460.418212890625,
        485.8483581542969,
        1476.769775390625,
        522.5640258789062
      ],
      "mask_area": 409
    },
    {
      "instance_id": 3,
      "class_name": "pedestrian",
      "class_id": 5,
      "score": 0.8855697512626648,
      "bbox": [
        1535.639892578125,
        496.6693115234375,
        1597.6580810546875,
        663.195556640625
      ],
      "mask_area": 5796
    },
    {
      "instance_id": 4,
      "class_name": "pedestrian",
      "class_id": 5,
      "score": 0.9019318222999573,
      "bbox": [
        1339.7547607421875,
        418.96173095703125,
        1452.17431640625,
        634.4725341796875
      ],
      "mask_area": 9011
    }
  ]
}