{
  "instances": [
    {
      "instance_id": 1,
      "class_name": "car",
      "class_id": 0,
      "score": 0.7356162071228027,
      "bbox": [
        708.36865234375,
        433.85455322265625,
        1026.3271484375,
        708.602783203125
      ],
      "mask_area": 53
    },
    {
      "instance_id": 2,
      "class_name": "truck",
      "class_id": 1,
      "score": 0.859830915927887,
      "bbox": [
        706.498291015625,
        433.9892578125,
        1029.182373046875,
        708.8970947265625
      ],
      "mask_area": 70951
    },
    {
      "instance_id": 3,
      "class_name": "truck",
      "class_id": 1,
      "score": 0.9750905632972717,
      "bbox": [
        918.299072265625,
        223.83033752441406,
        1601.411376953125,
        735.4916381835938
      ],
      "mask_area": 241924
    }
  ]
}