{
  "instances": [
    {
      "instance_id": 1,
      "class_name": "pedestrian",
      "class_id": 5,
      "score": 0.5118240714073181,
      "bbox": [
        69.5176010131836,
        422.19818115234375,
        83.02861785888672,
        437.25872802734375
      ],
      "mask_area": 148
    },
    {
      "instance_id": 2,
      "class_name": "pedestrian",
      "class_id": 5,
      "score": 0.5206068158149719,
      "bbox": [
        944.2279052734375,
        415.1485595703125,
        962.1258544921875,
        439.05535888671875
      ],
      "mask_area": 365
    },
    {
      "instance_id": 3,
      "class_name": "car",
      "class_id": 0,
      "score": 0.5479575395584106,
      "bbox": [
        -2.8341352939605713,
        430.33038330078125,
        163.39988708496094,
        541.5650634765625
      ],
      "mask_area": 3202
    },
    {
      "instance_id": 4,
      "class_name": "pedestrian",
      "class_id": 5,
      "score": 0.5767495036125183,
      "bbox": [
        620.7831420898438,
        417.8398742675781,
        647.120849609375,
        482.1571044921875
      ],
      "mask_area": 1214
    },
    {
      "instance_id": 5,
      "class_name": "pedestrian",
      "class_id": 5,
      "score": 0.6663181781768799,
      "bbox": [
        545.38037109375,
        416.5415344238281,
        565.5452880859375,
        481.43023681640625
      ],
      "mask_area": 956
    },
    {
      "instance_id": 6,
      "class_name": "pedestrian",
      "class_id": 5,
      "score": 0.6784648299217224,
      "bbox": [
        1415.372802734375,
        507.3260498046875,
        1449.4862060546875,
        602.4881591796875
      ],
      "mask_area": 2330
    },
    {
      "instance_id": 7,
      "class_name": "pedestrian",
      "class_id": 5,
      "score": 0.7461428046226501,
      "bbox": [
        1207.1160888671875,
        427.7151794433594,
        1242.9371337890625,
        492.9375
      ],
      "mask_area": 1155
    },
    {
      "instance_id": 8,
      "class_name": "pedestrian",
      "class_id": 5,
      "score": 0.7470370531082153,
      "bbox": [
        1321.9493408203125,
        444.4173889160156,
        1350.666015625,
        480.326171875
      ],
      "mask_area": 714
    },
    {
      "instance_id": 9,
      "class_name": "pedestrian",
      "class_id": 5,
      "score": 0.8115284442901611,
      "bbox": [
        1120.0926513671875,
        441.7640686035156,
        1143.7606201171875,
        478.1043395996094
      ],
      "mask_area": 596
    },
    {
      "instance_id": 10,
      "class_name": "pedestrian",
      "class_id": 5,
      "score": 0.8137100338935852,
      "bbox": [
        1304.1279296875,
        469.1185607910156,
        1327.6800537109375,
        573.6792602539062
      ],
      "mask_area": 1789
    },
    {
      "instance_id": 11,
      "class_name": "pedestrian",
      "class_id": 5,
      "score": 0.8258250951766968,
      "bbox": [
        1146.01318359375,
        441.55853271484375,
        1173.803466796875,
        478.36114501953125
      ],
      "mask_area": 709
    },
    {
      "instance_id": 12,
      "class_name": "pedestrian",
      "class_id": 5,
      "score": 0.8359315395355225,
      "bbox": [
        742.8046875,
        479.774658203125,
        782.5148315429688,
        590.830322265625
      ],
      "mask_area": 2506
    },
    {
      "instance_id": 13,
      "class_name": "bicycle",
      "class_id": 7,
      "score": 0.8373746275901794,
      "bbox": [
        1117.0770263671875,
        502.6684875488281,
        1224.0078125,
        558.197509765625
      ],
      "mask_area": 4003
    },
    {
      "instance_id": 14,
      "class_name": "pedestrian",
      "class_id": 5,
      "score": 0.8596199154853821,
      "bbox": [
        1518.4593505859375,
        453.54119873046875,
        1558.1348876953125,
        528.7828369140625
      ],
      "mask_area": 1580
    },
    {
      "instance_id": 15,
      "class_name": "pedestrian",
      "class_id": 5,
      "score": 0.8827806711196899,
      "bbox": [
        842.58544921875,
        501.67291259765625,
        876.5074462890625,
        596.2418212890625
      ],
      "mask_area": 2154
    },
    {
      "instance_id": 16,
      "class_name": "car",
      "class_id": 0,
      "score": 0.8986198306083679,
      "bbox": [
        635.0858154296875,
        458.4233703613281,
        782.1134033203125,
        526.7001953125
      ],
      "mask_area": 6301
    },
    {
      "instance_id": 17,
      "class_name": "car",
      "class_id": 0,
      "score": 0.9038229584693909,
      "bbox": [
        155.5123748779297,
        475.3846435546875,
        321.67626953125,
        577.7359008789062
      ],
      "mask_area": 11429
    },
    {
      "instance_id": 18,
      "class_name": "pedestrian",
      "class_id": 5,
      "score": 0.911038339138031,
      "bbox": [
        772.4779663085938,
        505.36676025390625,
        826.5205078125,
        676.0234985351562
      ],
      "mask_area": 6379
    },
    {
      "instance_id": 19,
      "class_name": "car",
      "class_id": 0,
      "score": 0.9250662922859192,
      "bbox": [
        -0.9730041027069092,
        433.07916259765625,
        167.08590698242188,
        754.5186157226562
      ],
      "mask_area": 44171
    },
    {
      "instance_id": 20,
      "class_name": "truck",
      "class_id": 1,
      "score": 0.9504830241203308,
      "bbox": [
        107.16166687011719,
        388.1088562011719,
        483.3793640136719,
        571.4968872070312
      ],
      "mask_area": 42625
    }
  ]
}