{
  "instances": [
    {
      "instance_id": 1,
      "class_name": "car",
      "class_id": 0,
      "score": 0.5262445211410522,
      "bbox": [
        515.3805541992188,
        439.1233825683594,
        643.821533203125,
        506.8116149902344
      ],
      "mask_area": 2961
    },
    {
      "instance_id": 2,
      "class_name": "car",
      "class_id": 0,
      "score": 0.5482877492904663,
      "bbox": [
        43.12651062011719,
        380.5383605957031,
        516.9052124023438,
        564.8291625976562
      ],
      "mask_area": 65802
    },
    {
      "instance_id": 3,
      "class_name": "pedestrian",
      "class_id": 5,
      "score": 0.7662474513053894,
      "bbox": [
        1011.8208618164062,
        437.0397644042969,
        1043.4149169921875,
        530.0064086914062
      ],
      "mask_area": 2058
    },
    {
      "instance_id": 4,
      "class_name": "pedestrian",
      "class_id": 5,
      "score": 0.7904940843582153,
      "bbox": [
        961.7952270507812,
        444.086669921875,
        997.4224243164062,
        526.583251953125
      ],
      "mask_area": 1995
    }
  ]
}