{
  "instances": [
    {
      "instance_id": 1,
      "class_name": "car",
      "class_id": 0,
      "score": 0.7269958853721619,
      "bbox": [
        1301.56005859375,
        507.94879150390625,
        1401.033203125,
        558.3373413085938
      ],
      "mask_area": 4299
    },
    {
      "instance_id": 2,
      "class_name": "car",
      "class_id": 0,
      "score": 0.7531489133834839,
      "bbox": [
        819.070068359375,
        482.4988708496094,
        879.4140014648438,
        525.2756958007812
      ],
      "mask_area": 2012
    },
    {
      "instance_id": 3,
      "class_name": "car",
      "class_id": 0,
      "score": 0.8595823049545288,
      "bbox": [
        957.6826171875,
        494.1452941894531,
        1113.879150390625,
        543.3135375976562
      ],
      "mask_area": 5288
    },
    {
      "instance_id": 4,
      "class_name": "car",
      "class_id": 0,
      "score": 0.9075629711151123,
      "bbox": [
        1168.384521484375,
        499.36810302734375,
        1311.451904296875,
        555.3458251953125
      ],
      "mask_area": 5935
    },
    {
      "instance_id": 5,
      "class_name": "car",
      "class_id": 0,
      "score": 0.9376437664031982,
      "bbox": [
        601.6340942382812,
        490.3316650390625,
        801.2559814453125,
        552.0225830078125
      ],
      "mask_area": 8894
    }
  ]
}