{
  "instances": [
    {
      "instance_id": 1,
      "class_name": "car",
      "class_id": 0,
      "score": 0.530413806438446,
      "bbox": [
        704.4541625976562,
        479.6819763183594,
        738.4170532226562,
        491.72894287109375
      ],
      "mask_area": 32
    },
    {
      "instance_id": 2,
      "class_name": "car",
      "class_id": 0,
      "score": 0.562646210193634,
      "bbox": [
        705.7708129882812,
        480.1310729980469,
        754.6558837890625,
        504.0625
      ],
      "mask_area": 407
    },
    {
      "instance_id": 3,
      "class_name": "car",
      "class_id": 0,
      "score": 0.6723911166191101,
      "bbox": [
        793.1420288085938,
        480.8695373535156,
        810.894287109375,
        493.5884704589844
      ],
      "mask_area": 201
    },
    {
      "instance_id": 4,
      "class_name": "car",
      "class_id": 0,
      "score": 0.8192626237869263,
      "bbox": [
        643.8802490234375,
        486.67047119140625,
        685.797119140625,
        513.8467407226562
      ],
      "mask_area": 894
    },
    {
      "instance_id": 5,
      "class_name": "car",
      "class_id": 0,
      "score": 0.8871455192565918,
      "bbox": [
        807.115478515625,
        480.4984436035156,
        856.3954467773438,
        526.2562866210938
      ],
      "mask_area": 1888
    },
    {
      "instance_id": 6,
      "class_name": "car",
      "class_id": 0,
      "score": 0.9132015109062195,
      "bbox": [
        678.7296142578125,
        489.2798156738281,
        755.5989379882812,
        544.3781127929688
      ],
      "mask_area": 3469
    },
    {
      "instance_id": 7,
      "class_name": "car",
      "class_id": 0,
      "score": 0.9652475118637085,
      "bbox": [
        294.47186279296875,
        499.8561096191406,
        641.3994750976562,
        693.7779541015625
      ],
      "mask_area": 48797
    }
  ]
}