{
  "instances": [
    {
      "instance_id": 1,
      "class_name": "car",
      "class_id": 0,
      "score": 0.7104233503341675,
      "bbox": [
        -1.1964335441589355,
        493.865478515625,
        28.58932113647461,
        550.0706176757812
      ],
      "mask_area": 1088
    },
    {
      "instance_id": 2,
      "class_name": "car",
      "class_id": 0,
      "score": 0.7467606663703918,
      "bbox": [
        904.9356689453125,
        324.9224548339844,
        1603.63623046875,
        805.4176025390625
      ],
      "mask_area": 216065
    },
    {
      "instance_id": 3,
      "class_name": "car",
      "class_id": 0,
      "score": 0.9092169404029846,
      "bbox": [
        -2.539181709289551,
        449.82080078125,
        648.9893798828125,
        739.7507934570312
      ],
      "mask_area": 135135
    }
  ]
}