{
  "instances": [
    {
      "instance_id": 1,
      "class_name": "truck",
      "class_id": 1,
      "score": 0.5257584452629089,
      "bbox": [
        717.5134887695312,
        462.87713623046875,
        761.8782348632812,
        497.3994140625
      ],
      "mask_area": 98
    },
    {
      "instance_id": 2,
      "class_name": "truck",
      "class_id": 1,
      "score": 0.5608341693878174,
      "bbox": [
        590.8743286132812,
        447.4883117675781,
        649.6361083984375,
        497.99609375
      ],
      "mask_area": 2175
    },
    {
      "instance_id": 3,
      "class_name": "truck",
      "class_id": 1,
      "score": 0.5803222060203552,
      "bbox": [
        889.2296752929688,
        432.4034729003906,
        957.1486206054688,
        500.5001525878906
      ],
      "mask_area": 41
    },
    {
      "instance_id": 4,
      "class_name": "car",
      "class_id": 0,
      "score": 0.5888477563858032,
      "bbox": [
        1046.103515625,
        467.1007385253906,
        1087.0692138671875,
        492.00225830078125
      ],
      "mask_area": 428
    },
    {
      "instance_id": 5,
      "class_name": "car",
      "class_id": 0,
      "score": 0.5946412682533264,
      "bbox": [
        1058.0400390625,
        466.9476318359375,
        1100.0816650390625,
        493.5443115234375
      ],
      "mask_area": 732
    },
    {
      "instance_id": 6,
      "class_name": "car",
      "class_id": 0,
      "score": 0.6197208762168884,
      "bbox": [
        1147.8843994140625,
        462.677734375,
        1236.3916015625,
        503.1993713378906
      ],
      "mask_area": 1665
    },
    {
      "instance_id": 7,
      "class_name": "car",
      "class_id": 0,
      "score": 0.6580029726028442,
      "bbox": [
        1183.099609375,
        466.06536865234375,
        1256.9327392578125,
        508.3354797363281
      ],
      "mask_area": 1693
    },
    {
      "instance_id": 8,
      "class_name": "car",
      "class_id": 0,
      "score": 0.6911770701408386,
      "bbox": [
        718.1177368164062,
        463.84112548828125,
        760.6483764648438,
        497.4049987792969
      ],
      "mask_area": 1117
    },
    {
      "instance_id": 9,
      "class_name": "car",
      "class_id": 0,
      "score": 0.6934601664543152,
      "bbox": [
        1242.7008056640625,
        460.8118896484375,
        1318.1102294921875,
        508.033447265625
      ],
      "mask_area": 2205
    },
    {
      "instance_id": 10,
      "class_name": "traffic_cone",
      "class_id": 8,
      "score": 0.7006503343582153,
      "bbox": [
        1284.228759765625,
        489.07025146484375,
        1298.7681884765625,
        526.6958618164062
      ],
      "mask_area": 399
    },
    {
      "instance_id": 11,
      "class_name": "car",
      "class_id": 0,
      "score": 0.7531391978263855,
      "bbox": [
        781.9600830078125,
        470.3519592285156,
        806.8099975585938,
        491.984619140625
      ],
      "mask_area": 461
    },
    {
      "instance_id": 12,
      "class_name": "car",
      "class_id": 0,
      "score": 0.7721449732780457,
      "bbox": [
        80.75570678710938,
        468.9689025878906,
        345.6314697265625,
        620.3186645507812
      ],
      "mask_area": 157
    },
    {
      "instance_id": 13,
      "class_name": "car",
      "class_id": 0,
      "score": 0.7987041473388672,
      "bbox": [
        1566.54931640625,
        535.4533081054688,
        1602.1124267578125,
        622.1201171875
      ],
      "mask_area": 2364
    },
    {
      "instance_id": 14,
      "class_name": "car",
      "class_id": 0,
      "score": 0.8349462747573853,
      "bbox": [
        612.1642456054688,
        475.42230224609375,
        684.1019897460938,
        521.3223876953125
      ],
      "mask_area": 2098
    },
    {
      "instance_id": 15,
      "class_name": "bus",
      "class_id": 2,
      "score": 0.8616719245910645,
      "bbox": [
        889.2714233398438,
        432.37921142578125,
        956.9603881835938,
        500.5042724609375
      ],
      "mask_area": 4035
    },
    {
      "instance_id": 16,
      "class_name": "truck",
      "class_id": 1,
      "score": 0.8646091222763062,
      "bbox": [
        80.3873519897461,
        468.7685852050781,
        346.24591064453125,
        620.2459106445312
      ],
      "mask_area": 29553
    },
    {
      "instance_id": 17,
      "class_name": "pedestrian",
      "class_id": 5,
      "score": 0.8705284595489502,
      "bbox": [
        653.7858276367188,
        469.3184509277344,
        685.7468872070312,
        539.4393310546875
      ],
      "mask_area": 988
    },
    {
      "instance_id": 18,
      "class_name": "car",
      "class_id": 0,
      "score": 0.9147078990936279,
      "bbox": [
        -1.4684468507766724,
        471.07952880859375,
        88.54415130615234,
        655.4834594726562
      ],
      "mask_area": 13186
    },
    {
      "instance_id": 19,
      "class_name": "car",
      "class_id": 0,
      "score": 0.9172886610031128,
      "bbox": [
        340.94171142578125,
        486.62347412109375,
        478.2846374511719,
        575.50927734375
      ],
      "mask_area": 10096
    }
  ]
}