{
  "instances": [
    {
      "instance_id": 1,
      "class_name": "truck",
      "class_id": 1,
      "score": 0.6103050112724304,
      "bbox": [
        -0.37348270416259766,
        376.6443176269531,
        326.1772155761719,
        536.6128540039062
      ],
      "mask_area": 125
    },
    {
      "instance_id": 2,
      "class_name": "car",
      "class_id": 0,
      "score": 0.6505725383758545,
      "bbox": [
        913.919189453125,
        423.7779541015625,
        982.4423828125,
        473.1786804199219
      ],
      "mask_area": 2702
    },
    {
      "instance_id": 3,
      "class_name": "car",
      "class_id": 0,
      "score": 0.8107855916023254,
      "bbox": [
        -0.5740523338317871,
        376.7754821777344,
        326.61651611328125,
        536.5888671875
      ],
      "mask_area": 31714
    },
    {
      "instance_id": 4,
      "class_name": "traffic_cone",
      "class_id": 8,
      "score": 0.9244645833969116,
      "bbox": [
        534.595947265625,
        536.9893188476562,
        589.1160278320312,
        643.9315795898438
      ],
      "mask_area": 2834
    },
    {
      "instance_id": 5,
      "class_name": "traffic_cone",
      "class_id": 8,
      "score": 0.9256095290184021,
      "bbox": [
        495.47900390625,
        532.43701171875,
        547.6594848632812,
        636.2299194335938
      ],
      "mask_area": 2626
    },
    {
      "instance_id": 6,
      "class_name": "traffic_cone",
      "class_id": 8,
      "score": 0.9392727613449097,
      "bbox": [
        630.8092651367188,
        549.57666015625,
        707.4730224609375,
        666.6844482421875
      ],
      "mask_area": 3506
    },
    {
      "instance_id": 7,
      "class_name": "traffic_cone",
      "class_id": 8,
      "score": 0.9415460824966431,
      "bbox": [
        580.6491088867188,
        543.13916015625,
        647.4745483398438,
        653.004150390625
      ],
      "mask_area": 3060
    },
    {
      "instance_id": 8,
      "class_name": "traffic_cone",
      "class_id": 8,
      "score": 0.9438133239746094,
      "bbox": [
        769.6682739257812,
        596.5597534179688,
        848.8699951171875,
        741.4971923828125
      ],
      "mask_area": 5216
    },
    {
      "instance_id": 9,
      "class_name": "traffic_cone",
      "class_id": 8,
      "score": 0.9467529654502869,
      "bbox": [
        428.01824951171875,
        700.2933349609375,
        511.45721435546875,
        900.2531127929688
      ],
      "mask_area": 10130
    }
  ]
}