{
  "instances": [
    {
      "instance_id": 1,
      "class_name": "pedestrian",
      "class_id": 5,
      "score": 0.5996125340461731,
      "bbox": [
        344.26824951171875,
        524.2491455078125,
        373.77789306640625,
        561.6944580078125
      ],
      "mask_area": 833
    },
    {
      "instance_id": 2,
      "class_name": "pedestrian",
      "class_id": 5,
      "score": 0.8002436757087708,
      "bbox": [
        261.685546875,
        512.9212036132812,
        300.1482849121094,
        646.8592529296875
      ],
      "mask_area": 3400
    },
    {
      "instance_id": 3,
      "class_name": "car",
      "class_id": 0,
      "score": 0.8584692478179932,
      "bbox": [
        1402.86669921875,
        498.72491455078125,
        1601.5821533203125,
        619.7740478515625
      ],
      "mask_area": 18358
    }
  ]
}