{
  "instances": [
    {
      "instance_id": 1,
      "class_name": "car",
      "class_id": 0,
      "score": 0.6968047022819519,
      "bbox": [
        117.34815979003906,
        459.3097229003906,
        226.46603393554688,
        517.1104736328125
      ],
      "mask_area": 3415
    },
    {
      "instance_id": 2,
      "class_name": "car",
      "class_id": 0,
      "score": 0.9116787910461426,
      "bbox": [
        538.201171875,
        455.0782165527344,
        813.8444213867188,
        555.863525390625
      ],
      "mask_area": 20200
    }
  ]
}