{
  "instances": [
    {
      "instance_id": 1,
      "class_name": "car",
      "class_id": 0,
      "score": 0.5911701321601868,
      "bbox": [
        753.124267578125,
        495.5229797363281,
        770.6428833007812,
        508.4311828613281
      ],
      "mask_area": 84
    },
    {
      "instance_id": 2,
      "class_name": "car",
      "class_id": 0,
      "score": 0.6573371291160583,
      "bbox": [
        781.0286254882812,
        497.04107666015625,
        795.6414794921875,
        510.5775146484375
      ],
      "mask_area": 153
    },
    {
      "instance_id": 3,
      "class_name": "car",
      "class_id": 0,
      "score": 0.8811349868774414,
      "bbox": [
        730.6409301757812,
        496.6831359863281,
        771.2968139648438,
        528.14404296875
      ],
      "mask_area": 1020
    },
    {
      "instance_id": 4,
      "class_name": "car",
      "class_id": 0,
      "score": 0.897004246711731,
      "bbox": [
        792.7778930664062,
        490.8437805175781,
        833.2980346679688,
        528.52001953125
      ],
      "mask_area": 1254
    },
    {
      "instance_id": 5,
      "class_name": "car",
      "class_id": 0,
      "score": 0.9198217391967773,
      "bbox": [
        189.72242736816406,
        504.2923583984375,
        349.89825439453125,
        570.1641845703125
      ],
      "mask_area": 7588
    },
    {
      "instance_id": 6,
      "class_name": "pedestrian",
      "class_id": 5,
      "score": 0.9322772026062012,
      "bbox": [
        1449.7393798828125,
        484.47222900390625,
        1514.449462890625,
        659.1964721679688
      ],
      "mask_area": 6526
    },
    {
      "instance_id": 7,
      "class_name": "pedestrian",
      "class_id": 5,
      "score": 0.9367628693580627,
      "bbox": [
        1366.241455078125,
        498.5205078125,
        1445.4071044921875,
        671.5509033203125
      ],
      "mask_area": 5814
    },
    {
      "instance_id": 8,
      "class_name": "bus",
      "class_id": 2,
      "score": 0.9397720098495483,
      "bbox": [
        -0.7105052471160889,
        378.4404296875,
        158.04283142089844,
        563.5178833007812
      ],
      "mask_area": 25214
    }
  ]
}